{"name":"30以下的平方數","questions":[{"question":"1²=?","answer":1},{"question":"2²=?","answer":4},{"question":"3²=?","answer":9},{"question":"4²=?","answer":16},{"question":"5²=?","answer":25},{"question":"6²=?","answer":36},{"question":"7²=?","answer":49},{"question":"8²=?","answer":64},{"question":"9²=?","answer":81},{"question":"10²=?","answer":100},{"question":"11²=?","answer":121},{"question":"12²=?","answer":144},{"question":"13²=?","answer":169},{"question":"14²=?","answer":196},{"question":"15²=?","answer":225},{"question":"16²=?","answer":256},{"question":"17²=?","answer":289},{"question":"18²=?","answer":324},{"question":"19²=?","answer":361},{"question":"20²=?","answer":400},{"question":"21²=?","answer":441},{"question":"22²=?","answer":484},{"question":"23²=?","answer":529},{"question":"24²=?","answer":576},{"question":"25²=?","answer":625},{"question":"26²=?","answer":676},{"question":"27²=?","answer":729},{"question":"28²=?","answer":784},{"question":"29²=?","answer":841},{"question":"30²=?","answer":900}]}